[
  {
    "min": 0,
    "max": 10,
    "message": "You're on fire! Let's ignite this journey!"
  },
  {
    "min": 11,
    "max": 25,
    "message": "Fantastic! Keep up the amazing momentum!"
  },
  {
    "min": 26,
    "max": 40,
    "message": "Woohoo! Progressing with unstoppable energy!"
  },
  {
    "min": 41,
    "max": 55,
    "message": "Halfway there! You're cruising like a champion!"
  },
  {
    "min": 56,
    "max": 70,
    "message": "Incredible work! You're smashing goals left and right!"
  },
  {
    "min": 71,
    "max": 99,
    "message": "Almost done! You're a rockstar!"
  },
  {
    "min": 100,
    "max": 100,
    "message": "Victory dance time!"
  }
]
